tox_travis/__init__.py
tox_travis/after.py
tox_travis/envlist.py
tox_travis/hacks.py
tox_travis/hooks.py
tox_travis/utils.py
tox_travis-0.11.dist-info/METADATA
tox_travis-0.11.dist-info/RECORD
tox_travis-0.11.dist-info/WHEEL
tox_travis-0.11.dist-info/entry_points.txt
tox_travis-0.11.dist-info/top_level.txt
